cs/cache.py
cs_cache-20250111.dist-info/WHEEL
cs_cache-20250111.dist-info/METADATA
cs_cache-20250111.dist-info/RECORD
