Metadata-Version: 2.3
Name: cs-cache
Version: 20250111
Summary: A few caching data structures and other lossy things with capped sizes.
Keywords: python2,python3
Author-email: Cameron Simpson <cs@cskk.id.au>
Classifier: Programming Language :: Python
Classifier: Programming Language :: Python :: 3
Classifier: Development Status :: 4 - Beta
Classifier: Intended Audience :: Developers
Classifier: Operating System :: OS Independent
Classifier: Topic :: Software Development :: Libraries :: Python Modules
Classifier: License :: OSI Approved :: GNU General Public License v3 or later (GPLv3+)
Requires-Dist: cs.context>=20240630
Requires-Dist: cs.deco>=20250103
Requires-Dist: cs.fileutils>=20250103
Requires-Dist: cs.fs>=20241122
Requires-Dist: cs.gimmicks>=20240316
Requires-Dist: cs.hashindex>=20241207
Requires-Dist: cs.lex>=20250103
Requires-Dist: cs.pfx>=20241208
Requires-Dist: cs.queues>=20250103
Requires-Dist: cs.resources>=20250103
Requires-Dist: cs.result>=20250103
Requires-Dist: cs.seq>=20250103
Requires-Dist: icontract
Project-URL: MonoRepo Commits, https://bitbucket.org/cameron_simpson/css/commits/branch/main
Project-URL: Monorepo Git Mirror, https://github.com/cameron-simpson/css
Project-URL: Monorepo Hg/Mercurial Mirror, https://hg.sr.ht/~cameron-simpson/css
Project-URL: Source, https://github.com/cameron-simpson/css/blob/main/lib/python/cs/cache.py
